{
    "staticDynVersion": "_7_2_2",
    "isLoginFlag": false,
    "recommend": "{\"waterFlow\":\"0\",\"code\":\"0\",\"wareInfoList\":[{\"adword\":\"\",\"presaleWare\":0,\"isDotScheme\":false,\"jdShop\":false,\"sourceValueFeedback\":\"{\\\"sid\\\":\\\"0\\\",\\\"index\\\":\\\"0\\\",\\\"source\\\":\\\"0\\\",\\\"page\\\":\\\"8\\\",\\\"reqsig\\\":\\\"2053e9f6fb6f81ebcae364a3d86d974c63a944bd\\\",\\\"flow\\\":\\\"20\\\",\\\"skuid\\\":\\\"16463451903\\\",\\\"expid\\\":\\\"100\\\"}\",\"venderId\":\"67259\",\"jdPrice\":\"38.00\",\"isPinGouWare\":false,\"followCount\":\"\",\"good\":\"100%\",\"recomReasonTab\":\"tab_var_071\",\"flow\":\"20\",\"imageurlType\":0,\"icon618\":\"1\",\"isSamWare\":false,\"priceColor\":\"232326\",\"isShowIcon618\":true,\"abt\":\"\",\"recomText\":\"\",\"iconC\":\"tab_060\",\"endRemainTime\":0,\"priceIcon\":\"http:\/\/m.360buyimg.com\/mobilecms\/jfs\/t3331\/312\/2223477324\/2115\/42d33f4b\/584539b7N0c09e061.png\",\"wareId\":\"16463451903\",\"expid\":\"100\",\"couponSortType\":0,\"sourceValue\":\"8_0_16463451903_100_20_0_0_大家都在买的热销商品_2053e9f6fb6f81ebcae364a3d86d974c63a944bd_114\",\"isFeedBackSlide\":0,\"category1\":\"9987\",\"category3\":\"867\",\"category2\":\"830\",\"canAddCart\":\"0\",\"icon618Img\":\"\/\/m.360buyimg.com\/cc\/jfs\/t18418\/267\/2552089660\/923\/5efef8f7\/5afbd692Nda78a09e.png\",\"sourceValueSimilar\":\"0_.6_0_16463451903_100_8_20_0_0\",\"wname\":\"图拉斯 苹果X钢化膜iPhoneX全屏全覆盖6D抗蓝光防爆玻璃手机10贴膜前后背膜 【黑色】高清款★真6D全屏隐形膜\",\"stockStateId\":33,\"promotion\":\"false\",\"markFlag\":0,\"isPlusWare\":true,\"remainNum\":-1,\"canNegFeedback\":\"1\",\"tryPlusPrice\":\"29.80\",\"feminine\":false,\"similarEnter\":\"1\",\"canFreeRead\":\"false\",\"imageurl\":\"http:\/\/m.360buyimg.com\/mobilecms\/s276x276_jfs\/t18322\/56\/2409254965\/445456\/e5ba660f\/5af4683eNea1e229b.jpg!q70.jpg\",\"mainVideoId\":\"3896029\",\"sid\":\"0\",\"mp\":0,\"startRemainTime\":0,\"itemType\":0,\"recomReason\":\"大家都在买的热销商品\",\"commentCount\":\"113870\",\"source\":\"0\",\"reqsig\":\"2053e9f6fb6f81ebcae364a3d86d974c63a944bd\",\"book\":\"false\",\"clickUrl\":\"http:\/\/mercury.jd.com\/log.gif?t=rec.619128&v=src=rec$action=1$reqsig=2053e9f6fb6f81ebcae364a3d86d974c63a944bd$enb=1$sku=0$p=619128$pin=$uuid=15160196181341028780571$csku=16463451903$index=0$st=0$adcli=$expid=100$im=&rid=1752306307541895661&ver=1&sig=87ae52141223c20fcfd536555e4acd1e74c4ea94\",\"exposureSourceValue\":\"16463451903#2053e9f6fb6f81ebcae364a3d86d974c63a944bd#0#20#0#1#100#领券#114#8#0#1\"},{\"adword\":\"\",\"presaleWare\":0,\"isDotScheme\":false,\"markHeight\":13,\"jdShop\":false,\"sourceValueFeedback\":\"{\\\"sid\\\":\\\"0\\\",\\\"index\\\":\\\"1\\\",\\\"source\\\":\\\"0\\\",\\\"page\\\":\\\"8\\\",\\\"reqsig\\\":\\\"2053e9f6fb6f81ebcae364a3d86d974c63a944bd\\\",\\\"flow\\\":\\\"20\\\",\\\"skuid\\\":\\\"771351\\\",\\\"expid\\\":\\\"100\\\"}\",\"venderId\":\"1000001825\",\"jdPrice\":\"99.00\",\"isPinGouWare\":false,\"followCount\":\"\",\"good\":\"99%\",\"recomReasonTab\":\"tab_var_071\",\"flow\":\"20\",\"imageurlType\":0,\"priceColor\":\"232326\",\"isSamWare\":false,\"abt\":\"\",\"benefitImageUrl\":\"http:\/\/img30.360buyimg.com\/jgsq-productsoa\/jfs\/t14332\/56\/2342045055\/8025\/c40894c7\/5a990af1N2719ee6f.png\",\"endRemainTime\":0,\"priceIcon\":\"http:\/\/m.360buyimg.com\/mobilecms\/jfs\/t3331\/312\/2223477324\/2115\/42d33f4b\/584539b7N0c09e061.png\",\"wareId\":\"771351\",\"expid\":\"100\",\"couponSortType\":0,\"sourceValue\":\"8_1_771351_100_20_0_0_大家都在买的热销商品_2053e9f6fb6f81ebcae364a3d86d974c63a944bd_114\",\"isFeedBackSlide\":0,\"benefitTime\":\"6.9-6.13\",\"category1\":\"1620\",\"category3\":\"1661\",\"category2\":\"1624\",\"canAddCart\":\"0\",\"markImageUrl\":\"http:\/\/m.360buyimg.com\/mobilecms\/jfs\/t3802\/184\/2262265095\/4363\/20cc83a\/584675ccNb39899f9.png\",\"sourceValueSimilar\":\"0_.6_1_771351_100_8_20_0_0\",\"wname\":\"绿之源 6000g360°室内装修安全卫士活性炭包 新房吸去除甲醛清除剂竹炭包净化除味碳包\",\"stockStateId\":33,\"markWidth\":50,\"promotion\":\"false\",\"benefitTitle\":\"家居好物满199减100\",\"markFlag\":1,\"isPlusWare\":true,\"remainNum\":-1,\"canNegFeedback\":\"1\",\"tryPlusPrice\":\"89.00\",\"feminine\":false,\"similarEnter\":\"1\",\"canFreeRead\":\"false\",\"imageurl\":\"http:\/\/m.360buyimg.com\/mobilecms\/s276x276_jfs\/t14893\/155\/1278351413\/341819\/8f5d320f\/5a4b3399N8c594586.jpg!q70.jpg\",\"sid\":\"0\",\"mp\":0,\"startRemainTime\":0,\"itemType\":0,\"recomReason\":\"大家都在买的热销商品\",\"commentCount\":\"430167\",\"source\":\"0\",\"reqsig\":\"2053e9f6fb6f81ebcae364a3d86d974c63a944bd\",\"book\":\"false\",\"clickUrl\":\"http:\/\/mercury.jd.com\/log.gif?t=rec.619128&v=src=rec$action=1$reqsig=2053e9f6fb6f81ebcae364a3d86d974c63a944bd$enb=1$sku=0$p=619128$pin=$uuid=15160196181341028780571$csku=771351$index=1$st=0$adcli=$expid=100$im=&rid=1752306307541895661&ver=1&sig=769e2afdde7e02086bd6302a8c79b6b905cd32c8\",\"exposureSourceValue\":\"771351#2053e9f6fb6f81ebcae364a3d86d974c63a944bd#0#20#0#1#100#-100#114#8#1#0\",\"wareType\":8},{\"adword\":\"\",\"presaleWare\":0,\"isDotScheme\":false,\"sourceValueFeedback\":\"{\\\"sid\\\":\\\"0\\\",\\\"index\\\":\\\"2\\\",\\\"source\\\":\\\"0\\\",\\\"page\\\":\\\"8\\\",\\\"reqsig\\\":\\\"2053e9f6fb6f81ebcae364a3d86d974c63a944bd\\\",\\\"flow\\\":\\\"20\\\",\\\"skuid\\\":\\\"2138307\\\",\\\"expid\\\":\\\"100\\\"}\",\"jdShop\":false,\"venderId\":\"1000000864\",\"followCount\":\"\",\"jdPrice\":\"17.90\",\"isPinGouWare\":false,\"good\":\"98%\",\"flow\":\"20\",\"imageurlType\":0,\"icon618\":\"1\",\"isSamWare\":false,\"isShowIcon618\":true,\"abt\":\"\",\"recomText\":\"\",\"iconC\":\"tab_060\",\"endRemainTime\":0,\"wareId\":\"2138307\",\"expid\":\"100\",\"couponSortType\":0,\"sourceValue\":\"8_2_2138307_100_20_0_0_-100_2053e9f6fb6f81ebcae364a3d86d974c63a944bd_-100\",\"isFeedBackSlide\":0,\"category1\":\"9987\",\"category3\":\"867\",\"category2\":\"830\",\"canAddCart\":\"0\",\"icon618Img\":\"\/\/m.360buyimg.com\/cc\/jfs\/t18418\/267\/2552089660\/923\/5efef8f7\/5afbd692Nda78a09e.png\",\"sourceValueSimilar\":\"0_.6_2_2138307_100_8_20_0_0\",\"wname\":\"亿色(ESR) iPhone8 Plus\/7Plus\/6s Plus钢化膜 苹果8Plus\/7plus\/6sPlus钢化膜 非全屏覆盖高清手机贴膜前膜\",\"stockStateId\":33,\"promotion\":\"false\",\"markFlag\":0,\"isPlusWare\":false,\"remainNum\":-1,\"canNegFeedback\":\"1\",\"feminine\":false,\"similarEnter\":\"1\",\"canFreeRead\":\"false\",\"imageurl\":\"http:\/\/m.360buyimg.com\/mobilecms\/s276x276_jfs\/t17647\/162\/443819944\/372932\/a69f3d1f\/5a790817Naa391d36.jpg!q70.jpg\",\"sid\":\"0\",\"mainVideoId\":\"4261255\",\"mp\":0,\"startRemainTime\":0,\"itemType\":0,\"commentCount\":\"397607\",\"source\":\"0\",\"reqsig\":\"2053e9f6fb6f81ebcae364a3d86d974c63a944bd\",\"book\":\"false\",\"clickUrl\":\"http:\/\/mercury.jd.com\/log.gif?t=rec.619128&v=src=rec$action=1$reqsig=2053e9f6fb6f81ebcae364a3d86d974c63a944bd$enb=1$sku=0$p=619128$pin=$uuid=15160196181341028780571$csku=2138307$index=2$st=0$adcli=$expid=100$im=&rid=1752306307541895661&ver=1&sig=ee0578d3b166969d5503d2f0fa8c290d7721e3a4\",\"exposureSourceValue\":\"2138307#2053e9f6fb6f81ebcae364a3d86d974c63a944bd#0#20#0#0#100#领券#-100#8#2#1\"},{\"adword\":\"\",\"presaleWare\":0,\"isDotScheme\":false,\"sourceValueFeedback\":\"{\\\"sid\\\":\\\"0\\\",\\\"index\\\":\\\"3\\\",\\\"source\\\":\\\"0\\\",\\\"page\\\":\\\"8\\\",\\\"reqsig\\\":\\\"2053e9f6fb6f81ebcae364a3d86d974c63a944bd\\\",\\\"flow\\\":\\\"20\\\",\\\"skuid\\\":\\\"5398586\\\",\\\"expid\\\":\\\"100\\\"}\",\"jdShop\":false,\"venderId\":\"1000093468\",\"followCount\":\"\",\"jdPrice\":\"61.80\",\"isPinGouWare\":false,\"good\":\"100%\",\"flow\":\"20\",\"imageurlType\":0,\"icon618\":\"1\",\"isSamWare\":false,\"abt\":\"\",\"isShowIcon618\":true,\"endRemainTime\":0,\"wareId\":\"5398586\",\"expid\":\"100\",\"couponSortType\":0,\"sourceValue\":\"8_3_5398586_100_20_0_0_-100_2053e9f6fb6f81ebcae364a3d86d974c63a944bd_-100\",\"isFeedBackSlide\":0,\"category1\":\"1620\",\"category3\":\"1661\",\"category2\":\"1624\",\"canAddCart\":\"0\",\"icon618Img\":\"\/\/m.360buyimg.com\/cc\/jfs\/t18418\/267\/2552089660\/923\/5efef8f7\/5afbd692Nda78a09e.png\",\"sourceValueSimilar\":\"0_.6_3_5398586_100_8_20_0_0\",\"wname\":\"山山活性炭7000g家居除异味 装修除甲醛新房除味竹炭包家用碳去味吸甲醛清除剂\",\"stockStateId\":33,\"promotion\":\"false\",\"markFlag\":0,\"isPlusWare\":false,\"remainNum\":-1,\"canNegFeedback\":\"1\",\"feminine\":false,\"similarEnter\":\"1\",\"canFreeRead\":\"false\",\"imageurl\":\"http:\/\/m.360buyimg.com\/mobilecms\/s276x276_jfs\/t17239\/295\/488752289\/189911\/4ee2518c\/5a93bb15N5075ebb7.jpg!q70.jpg\",\"sid\":\"0\",\"mainVideoId\":\"635680\",\"mp\":0,\"startRemainTime\":0,\"itemType\":0,\"commentCount\":\"63824\",\"source\":\"0\",\"reqsig\":\"2053e9f6fb6f81ebcae364a3d86d974c63a944bd\",\"book\":\"false\",\"clickUrl\":\"http:\/\/mercury.jd.com\/log.gif?t=rec.619128&v=src=rec$action=1$reqsig=2053e9f6fb6f81ebcae364a3d86d974c63a944bd$enb=1$sku=0$p=619128$pin=$uuid=15160196181341028780571$csku=5398586$index=3$st=0$adcli=$expid=100$im=&rid=1752306307541895661&ver=1&sig=cea84c453b5e400a8f6dfe57c67244540d567a33\",\"exposureSourceValue\":\"5398586#2053e9f6fb6f81ebcae364a3d86d974c63a944bd#0#20#0#0#100#-100#-100#8#3#1\"},{\"adword\":\"\",\"presaleWare\":0,\"isDotScheme\":false,\"sourceValueFeedback\":\"{\\\"sid\\\":\\\"0\\\",\\\"index\\\":\\\"4\\\",\\\"source\\\":\\\"0\\\",\\\"page\\\":\\\"8\\\",\\\"reqsig\\\":\\\"2053e9f6fb6f81ebcae364a3d86d974c63a944bd\\\",\\\"flow\\\":\\\"20\\\",\\\"skuid\\\":\\\"10016358805\\\",\\\"expid\\\":\\\"100\\\"}\",\"jdShop\":false,\"venderId\":\"52513\",\"followCount\":\"\",\"jdPrice\":\"48.00\",\"isPinGouWare\":false,\"good\":\"98%\",\"flow\":\"20\",\"imageurlType\":0,\"isSamWare\":false,\"abt\":\"\",\"benefitImageUrl\":\"http:\/\/img30.360buyimg.com\/jgsq-productsoa\/jfs\/t14332\/56\/2342045055\/8025\/c40894c7\/5a990af1N2719ee6f.png\",\"endRemainTime\":0,\"wareId\":\"10016358805\",\"expid\":\"100\",\"couponSortType\":0,\"sourceValue\":\"8_4_10016358805_100_20_0_0_-100_2053e9f6fb6f81ebcae364a3d86d974c63a944bd_-100\",\"isFeedBackSlide\":0,\"benefitTime\":\"6.17-6.20\",\"category1\":\"1620\",\"category3\":\"11965\",\"category2\":\"11158\",\"canAddCart\":\"0\",\"sourceValueSimilar\":\"0_.6_4_10016358805_100_8_20_0_0\",\"wname\":\"2片装大号3d立体砖纹自粘式墙贴纸客厅卧室电视背景墙加厚壁纸70*77cm 白色大号 两片装\",\"stockStateId\":33,\"promotion\":\"false\",\"benefitTitle\":\"居家生活跨万店3件7折\",\"markFlag\":1,\"isPlusWare\":false,\"remainNum\":-1,\"canNegFeedback\":\"1\",\"feminine\":false,\"similarEnter\":\"1\",\"canFreeRead\":\"false\",\"imageurl\":\"http:\/\/m.360buyimg.com\/mobilecms\/s276x276_jfs\/t19531\/349\/2711647505\/371715\/e00f8d87\/5b062423Naba7e523.jpg!q70.jpg\",\"sid\":\"0\",\"mainVideoId\":\"8797449\",\"mp\":0,\"startRemainTime\":0,\"itemType\":0,\"commentCount\":\"525\",\"source\":\"0\",\"reqsig\":\"2053e9f6fb6f81ebcae364a3d86d974c63a944bd\",\"book\":\"false\",\"clickUrl\":\"http:\/\/mercury.jd.com\/log.gif?t=rec.619128&v=src=rec$action=1$reqsig=2053e9f6fb6f81ebcae364a3d86d974c63a944bd$enb=1$sku=0$p=619128$pin=$uuid=15160196181341028780571$csku=10016358805$index=4$st=0$adcli=$expid=100$im=&rid=1752306307541895661&ver=1&sig=e0efa69414ab1246eb64c35f947487d01eb00ca\",\"exposureSourceValue\":\"10016358805#2053e9f6fb6f81ebcae364a3d86d974c63a944bd#0#20#0#0#100#-100#-100#8#4#0\"},{\"presaleWare\":0,\"stockStateId\":33,\"wname\":\"星特朗CELESTRON 显微镜专业学生儿童便携360度可旋转多用途生物640倍\",\"adword\":\"\",\"isDotScheme\":false,\"jdShop\":false,\"sourceValueFeedback\":\"{\\\"sid\\\":\\\"0\\\",\\\"index\\\":\\\"5\\\",\\\"source\\\":\\\"0\\\",\\\"page\\\":\\\"8\\\",\\\"reqsig\\\":\\\"2053e9f6fb6f81ebcae364a3d86d974c63a944bd\\\",\\\"flow\\\":\\\"20\\\",\\\"skuid\\\":\\\"28866860321\\\",\\\"expid\\\":\\\"100\\\"}\",\"promotion\":\"false\",\"venderId\":\"601330\",\"isPinGouWare\":false,\"jdPrice\":\"511.00\",\"followCount\":\"\",\"good\":\"100%\",\"flow\":\"20\",\"markFlag\":0,\"imageurlType\":0,\"isPlusWare\":false,\"remainNum\":-1,\"isSamWare\":false,\"abt\":\"\",\"canNegFeedback\":\"1\",\"iconC\":\"tab_060\",\"recomText\":\"\",\"endRemainTime\":0,\"similarEnter\":\"1\",\"feminine\":false,\"canFreeRead\":\"false\",\"imageurl\":\"http:\/\/m.360buyimg.com\/mobilecms\/s276x276_jfs\/t21922\/87\/1087902061\/274270\/103f27d7\/5b1f9eddN6ac66526.jpg!q70.jpg\",\"wareId\":\"28866860321\",\"expid\":\"100\",\"couponSortType\":0,\"sourceValue\":\"8_5_28866860321_100_20_0_0_-100_2053e9f6fb6f81ebcae364a3d86d974c63a944bd_-100\",\"sid\":\"0\",\"mp\":0,\"startRemainTime\":0,\"itemType\":0,\"isFeedBackSlide\":0,\"category1\":\"1318\",\"category3\":\"1480\",\"commentCount\":\"88\",\"canAddCart\":\"0\",\"category2\":\"1462\",\"source\":\"0\",\"sourceValueSimilar\":\"0_.6_5_28866860321_100_8_20_0_0\",\"reqsig\":\"2053e9f6fb6f81ebcae364a3d86d974c63a944bd\",\"book\":\"false\",\"clickUrl\":\"http:\/\/mercury.jd.com\/log.gif?t=rec.619128&v=src=rec$action=1$reqsig=2053e9f6fb6f81ebcae364a3d86d974c63a944bd$enb=1$sku=0$p=619128$pin=$uuid=15160196181341028780571$csku=28866860321$index=5$st=0$adcli=$expid=100$im=&rid=1752306307541895661&ver=1&sig=bf3fa19a6bd77c1b56f7485e016a22cfbc87235c\",\"exposureSourceValue\":\"28866860321#2053e9f6fb6f81ebcae364a3d86d974c63a944bd#0#20#0#0#100#领券#-100#8#5#0\"},{\"adword\":\"\",\"presaleWare\":0,\"isDotScheme\":false,\"jdShop\":false,\"sourceValueFeedback\":\"{\\\"sid\\\":\\\"0\\\",\\\"index\\\":\\\"6\\\",\\\"source\\\":\\\"0\\\",\\\"page\\\":\\\"8\\\",\\\"reqsig\\\":\\\"2053e9f6fb6f81ebcae364a3d86d974c63a944bd\\\",\\\"flow\\\":\\\"20\\\",\\\"skuid\\\":\\\"25797068573\\\",\\\"expid\\\":\\\"100\\\"}\",\"venderId\":\"615080\",\"jdPrice\":\"149.00\",\"isPinGouWare\":false,\"followCount\":\"\",\"good\":\"100%\",\"flow\":\"20\",\"imageurlType\":0,\"isSamWare\":false,\"priceColor\":\"232326\",\"abt\":\"\",\"benefitImageUrl\":\"http:\/\/img30.360buyimg.com\/jgsq-productsoa\/jfs\/t14332\/56\/2342045055\/8025\/c40894c7\/5a990af1N2719ee6f.png\",\"recomText\":\"满199元减20元\",\"iconC\":\"tab_020\",\"endRemainTime\":0,\"priceIcon\":\"http:\/\/m.360buyimg.com\/mobilecms\/jfs\/t3331\/312\/2223477324\/2115\/42d33f4b\/584539b7N0c09e061.png\",\"wareId\":\"25797068573\",\"expid\":\"100\",\"couponSortType\":0,\"sourceValue\":\"8_6_25797068573_100_20_0_0_-100_2053e9f6fb6f81ebcae364a3d86d974c63a944bd_-100\",\"isFeedBackSlide\":0,\"benefitTime\":\"6.17-6.20\",\"category1\":\"6196\",\"category3\":\"11977\",\"category2\":\"6214\",\"canAddCart\":\"0\",\"sourceValueSimilar\":\"0_.6_6_25797068573_100_8_20_0_0\",\"wname\":\"邻美 厨房置物架微波炉架落地不锈钢锅架厨房用品收纳储物架烤箱架 四层加强款长60宽35高100\",\"stockStateId\":33,\"promotion\":\"false\",\"benefitTitle\":\"居家生活跨万店3件7折\",\"markFlag\":1,\"isPlusWare\":true,\"remainNum\":-1,\"canNegFeedback\":\"1\",\"tryPlusPrice\":\"99.00\",\"feminine\":false,\"similarEnter\":\"1\",\"canFreeRead\":\"false\",\"imageurl\":\"http:\/\/m.360buyimg.com\/mobilecms\/s276x276_jfs\/t16867\/277\/2533389343\/426630\/5c02f6df\/5afaa509N0f2696a0.jpg!q70.jpg\",\"mainVideoId\":\"6828034\",\"sid\":\"0\",\"mp\":0,\"startRemainTime\":0,\"itemType\":0,\"commentCount\":\"1080\",\"source\":\"0\",\"reqsig\":\"2053e9f6fb6f81ebcae364a3d86d974c63a944bd\",\"book\":\"false\",\"clickUrl\":\"http:\/\/mercury.jd.com\/log.gif?t=rec.619128&v=src=rec$action=1$reqsig=2053e9f6fb6f81ebcae364a3d86d974c63a944bd$enb=1$sku=0$p=619128$pin=$uuid=15160196181341028780571$csku=25797068573$index=6$st=0$adcli=$expid=100$im=&rid=1752306307541895661&ver=1&sig=d27e5eb482bfb8ba9b11d17459baaf2c6908c16f\",\"exposureSourceValue\":\"25797068573#2053e9f6fb6f81ebcae364a3d86d974c63a944bd#0#20#0#1#100#满减#-100#8#6#0\"},{\"adword\":\"\",\"presaleWare\":0,\"isDotScheme\":false,\"jdShop\":false,\"sourceValueFeedback\":\"{\\\"sid\\\":\\\"0\\\",\\\"index\\\":\\\"7\\\",\\\"source\\\":\\\"0\\\",\\\"page\\\":\\\"8\\\",\\\"reqsig\\\":\\\"2053e9f6fb6f81ebcae364a3d86d974c63a944bd\\\",\\\"flow\\\":\\\"20\\\",\\\"skuid\\\":\\\"14359833029\\\",\\\"expid\\\":\\\"100\\\"}\",\"venderId\":\"88179\",\"followCount\":\"\",\"jdPrice\":\"149.00\",\"isPinGouWare\":false,\"good\":\"100%\",\"flow\":\"20\",\"imageurlType\":0,\"isSamWare\":false,\"abt\":\"\",\"benefitImageUrl\":\"http:\/\/img30.360buyimg.com\/jgsq-productsoa\/jfs\/t14332\/56\/2342045055\/8025\/c40894c7\/5a990af1N2719ee6f.png\",\"recomText\":\"\",\"iconC\":\"tab_060\",\"endRemainTime\":0,\"wareId\":\"14359833029\",\"expid\":\"100\",\"couponSortType\":0,\"sourceValue\":\"8_7_14359833029_100_20_0_0_-100_2053e9f6fb6f81ebcae364a3d86d974c63a944bd_-100\",\"isFeedBackSlide\":0,\"benefitTime\":\"6.11-6.14\",\"category1\":\"1318\",\"category3\":\"12122\",\"category2\":\"1466\",\"canAddCart\":\"0\",\"sourceValueSimilar\":\"0_.6_7_14359833029_100_8_20_0_0\",\"wname\":\"亿享 滑板车儿童四轮闪光加大PU轮2-3-6-12岁可折叠升降踏板车宝宝滑滑车 街舞超宽大轮款闪光轮赠送 护具+风车+彩带\",\"stockStateId\":33,\"promotion\":\"false\",\"benefitTitle\":\"领券满299-80 499-120\",\"markFlag\":1,\"isPlusWare\":false,\"remainNum\":-1,\"canNegFeedback\":\"1\",\"feminine\":false,\"similarEnter\":\"1\",\"canFreeRead\":\"false\",\"imageurl\":\"http:\/\/m.360buyimg.com\/mobilecms\/s276x276_jfs\/t22375\/332\/632773973\/138631\/fcd8b310\/5b1392d3Neb61b849.jpg!q70.jpg\",\"mainVideoId\":\"7706501\",\"sid\":\"0\",\"mp\":0,\"startRemainTime\":0,\"itemType\":0,\"commentCount\":\"4417\",\"source\":\"0\",\"reqsig\":\"2053e9f6fb6f81ebcae364a3d86d974c63a944bd\",\"book\":\"false\",\"clickUrl\":\"http:\/\/mercury.jd.com\/log.gif?t=rec.619128&v=src=rec$action=1$reqsig=2053e9f6fb6f81ebcae364a3d86d974c63a944bd$enb=1$sku=0$p=619128$pin=$uuid=15160196181341028780571$csku=14359833029$index=7$st=0$adcli=$expid=100$im=&rid=1752306307541895661&ver=1&sig=836ec563c84245ca226229bf51f81164b35269c6\",\"exposureSourceValue\":\"14359833029#2053e9f6fb6f81ebcae364a3d86d974c63a944bd#0#20#0#0#100#领券#-100#8#7#0\"},{\"presaleWare\":0,\"stockStateId\":33,\"wname\":\"【今日7折】  3d立体墙贴墙纸自粘砖纹防水防潮壁纸适用办公室儿童房客厅电视机背景墙 乳白色【新款】70*77CM\",\"adword\":\"\",\"isDotScheme\":false,\"jdShop\":false,\"sourceValueFeedback\":\"{\\\"sid\\\":\\\"0\\\",\\\"index\\\":\\\"8\\\",\\\"source\\\":\\\"0\\\",\\\"page\\\":\\\"8\\\",\\\"reqsig\\\":\\\"2053e9f6fb6f81ebcae364a3d86d974c63a944bd\\\",\\\"flow\\\":\\\"20\\\",\\\"skuid\\\":\\\"25897177123\\\",\\\"expid\\\":\\\"100\\\"}\",\"promotion\":\"false\",\"venderId\":\"733577\",\"isPinGouWare\":false,\"jdPrice\":\"13.90\",\"followCount\":\"\",\"good\":\"100%\",\"flow\":\"20\",\"markFlag\":0,\"imageurlType\":0,\"isPlusWare\":false,\"remainNum\":-1,\"isSamWare\":false,\"abt\":\"\",\"canNegFeedback\":\"1\",\"iconC\":\"tab_060\",\"endRemainTime\":0,\"similarEnter\":\"1\",\"feminine\":false,\"canFreeRead\":\"false\",\"imageurl\":\"http:\/\/m.360buyimg.com\/mobilecms\/s276x276_jfs\/t21193\/234\/48813249\/227069\/364513c2\/5af7c976N771ede57.jpg!q70.jpg\",\"wareId\":\"25897177123\",\"expid\":\"100\",\"couponSortType\":0,\"mainVideoId\":\"4512496\",\"sourceValue\":\"8_8_25897177123_100_20_0_0_-100_2053e9f6fb6f81ebcae364a3d86d974c63a944bd_-100\",\"sid\":\"0\",\"mp\":0,\"startRemainTime\":0,\"itemType\":0,\"isFeedBackSlide\":0,\"category1\":\"1620\",\"category3\":\"11965\",\"commentCount\":\"1260\",\"canAddCart\":\"0\",\"category2\":\"11158\",\"source\":\"0\",\"sourceValueSimilar\":\"0_.6_8_25897177123_100_8_20_0_0\",\"reqsig\":\"2053e9f6fb6f81ebcae364a3d86d974c63a944bd\",\"book\":\"false\",\"clickUrl\":\"http:\/\/mercury.jd.com\/log.gif?t=rec.619128&v=src=rec$action=1$reqsig=2053e9f6fb6f81ebcae364a3d86d974c63a944bd$enb=1$sku=0$p=619128$pin=$uuid=15160196181341028780571$csku=25897177123$index=8$st=0$adcli=$expid=100$im=&rid=1752306307541895661&ver=1&sig=308a3aee6a64bf6e908316813710523ce7ef04b0\",\"exposureSourceValue\":\"25897177123#2053e9f6fb6f81ebcae364a3d86d974c63a944bd#0#20#0#0#100#领券#-100#8#8#0\"},{\"adword\":\"\",\"presaleWare\":0,\"isDotScheme\":false,\"sourceValueFeedback\":\"{\\\"sid\\\":\\\"0\\\",\\\"index\\\":\\\"9\\\",\\\"source\\\":\\\"0\\\",\\\"page\\\":\\\"8\\\",\\\"reqsig\\\":\\\"2053e9f6fb6f81ebcae364a3d86d974c63a944bd\\\",\\\"flow\\\":\\\"20\\\",\\\"skuid\\\":\\\"17160936369\\\",\\\"expid\\\":\\\"100\\\"}\",\"jdShop\":false,\"venderId\":\"92019\",\"followCount\":\"\",\"jdPrice\":\"128.00\",\"isPinGouWare\":false,\"good\":\"99%\",\"flow\":\"20\",\"imageurlType\":0,\"isSamWare\":false,\"abt\":\"\",\"benefitImageUrl\":\"http:\/\/img30.360buyimg.com\/jgsq-productsoa\/jfs\/t14332\/56\/2342045055\/8025\/c40894c7\/5a990af1N2719ee6f.png\",\"endRemainTime\":0,\"wareId\":\"17160936369\",\"expid\":\"100\",\"couponSortType\":0,\"sourceValue\":\"8_9_17160936369_100_20_0_0_-100_2053e9f6fb6f81ebcae364a3d86d974c63a944bd_-100\",\"isFeedBackSlide\":0,\"benefitTime\":\"5.25-6.20\",\"category1\":\"1315\",\"category3\":\"9735\",\"category2\":\"1342\",\"canAddCart\":\"0\",\"sourceValueSimilar\":\"0_.6_9_17160936369_100_8_20_0_0\",\"wname\":\"南极人 牛仔裤男 修身弹力小脚裤简约休闲运动男士直筒裤夏季薄款水洗牛仔长裤男裤 5502 深蓝 31\",\"stockStateId\":33,\"promotion\":\"false\",\"benefitTitle\":\"618全球年中购物节\",\"markFlag\":1,\"isPlusWare\":false,\"remainNum\":-1,\"canNegFeedback\":\"1\",\"feminine\":false,\"similarEnter\":\"1\",\"canFreeRead\":\"false\",\"imageurl\":\"http:\/\/m.360buyimg.com\/mobilecms\/s276x276_jfs\/t19891\/355\/61708084\/383239\/3a19b1e4\/5ae2e8a9N455d1fb8.jpg!q70.jpg\",\"sid\":\"0\",\"mp\":0,\"startRemainTime\":0,\"itemType\":0,\"commentCount\":\"25304\",\"source\":\"0\",\"reqsig\":\"2053e9f6fb6f81ebcae364a3d86d974c63a944bd\",\"book\":\"false\",\"clickUrl\":\"http:\/\/mercury.jd.com\/log.gif?t=rec.619128&v=src=rec$action=1$reqsig=2053e9f6fb6f81ebcae364a3d86d974c63a944bd$enb=1$sku=0$p=619128$pin=$uuid=15160196181341028780571$csku=17160936369$index=9$st=0$adcli=$expid=100$im=&rid=1752306307541895661&ver=1&sig=40e4247f14c77e65a0ed8c320c64ac78e2843ece\",\"exposureSourceValue\":\"17160936369#2053e9f6fb6f81ebcae364a3d86d974c63a944bd#0#20#0#0#100#-100#-100#8#9#0\"},{\"adword\":\"\",\"presaleWare\":0,\"isDotScheme\":false,\"markHeight\":13,\"jdShop\":false,\"sourceValueFeedback\":\"{\\\"sid\\\":\\\"0\\\",\\\"index\\\":\\\"10\\\",\\\"source\\\":\\\"0\\\",\\\"page\\\":\\\"8\\\",\\\"reqsig\\\":\\\"2053e9f6fb6f81ebcae364a3d86d974c63a944bd\\\",\\\"flow\\\":\\\"20\\\",\\\"skuid\\\":\\\"678772\\\",\\\"expid\\\":\\\"100\\\"}\",\"venderId\":\"1000001825\",\"jdPrice\":\"49.00\",\"isPinGouWare\":false,\"followCount\":\"\",\"good\":\"98%\",\"flow\":\"20\",\"imageurlType\":0,\"priceColor\":\"232326\",\"isSamWare\":false,\"abt\":\"\",\"benefitImageUrl\":\"http:\/\/img30.360buyimg.com\/jgsq-productsoa\/jfs\/t14332\/56\/2342045055\/8025\/c40894c7\/5a990af1N2719ee6f.png\",\"endRemainTime\":0,\"priceIcon\":\"http:\/\/m.360buyimg.com\/mobilecms\/jfs\/t3331\/312\/2223477324\/2115\/42d33f4b\/584539b7N0c09e061.png\",\"wareId\":\"678772\",\"expid\":\"100\",\"couponSortType\":0,\"sourceValue\":\"8_10_678772_100_20_0_0_-100_2053e9f6fb6f81ebcae364a3d86d974c63a944bd_-100\",\"isFeedBackSlide\":0,\"benefitTime\":\"6.9-6.13\",\"category1\":\"1620\",\"category3\":\"1661\",\"category2\":\"1624\",\"canAddCart\":\"0\",\"markImageUrl\":\"http:\/\/m.360buyimg.com\/mobilecms\/jfs\/t3802\/184\/2262265095\/4363\/20cc83a\/584675ccNb39899f9.png\",\"sourceValueSimilar\":\"0_.6_10_678772_100_8_20_0_0\",\"wname\":\"绿之源 2000g净化王经济装活性炭包 室内新房装修吸去除甲醛清除剂竹炭包汽车净化除异味碳包\",\"stockStateId\":33,\"markWidth\":50,\"promotion\":\"false\",\"benefitTitle\":\"家居好物满199减100\",\"markFlag\":1,\"isPlusWare\":true,\"remainNum\":-1,\"canNegFeedback\":\"1\",\"tryPlusPrice\":\"44.90\",\"feminine\":false,\"similarEnter\":\"1\",\"canFreeRead\":\"false\",\"imageurl\":\"http:\/\/m.360buyimg.com\/mobilecms\/s276x276_jfs\/t18223\/319\/1981107752\/648674\/6bc07aeb\/5adec9e7N78698390.jpg!q70.jpg\",\"sid\":\"0\",\"mp\":0,\"startRemainTime\":0,\"itemType\":0,\"commentCount\":\"178156\",\"source\":\"0\",\"reqsig\":\"2053e9f6fb6f81ebcae364a3d86d974c63a944bd\",\"book\":\"false\",\"clickUrl\":\"http:\/\/mercury.jd.com\/log.gif?t=rec.619128&v=src=rec$action=1$reqsig=2053e9f6fb6f81ebcae364a3d86d974c63a944bd$enb=1$sku=0$p=619128$pin=$uuid=15160196181341028780571$csku=678772$index=10$st=0$adcli=$expid=100$im=&rid=1752306307541895661&ver=1&sig=c109dc4f21774f72053c0ffce5703e8dddf58904\",\"exposureSourceValue\":\"678772#2053e9f6fb6f81ebcae364a3d86d974c63a944bd#0#20#0#1#100#-100#-100#8#10#0\",\"wareType\":8},{\"adword\":\"\",\"presaleWare\":0,\"isDotScheme\":false,\"sourceValueFeedback\":\"{\\\"sid\\\":\\\"0\\\",\\\"index\\\":\\\"11\\\",\\\"source\\\":\\\"0\\\",\\\"page\\\":\\\"8\\\",\\\"reqsig\\\":\\\"2053e9f6fb6f81ebcae364a3d86d974c63a944bd\\\",\\\"flow\\\":\\\"20\\\",\\\"skuid\\\":\\\"4647632\\\",\\\"expid\\\":\\\"100\\\"}\",\"jdShop\":false,\"venderId\":\"0\",\"followCount\":\"\",\"jdPrice\":\"23.00\",\"isPinGouWare\":false,\"good\":\"98%\",\"flow\":\"20\",\"imageurlType\":0,\"isSamWare\":false,\"abt\":\"\",\"benefitImageUrl\":\"http:\/\/img30.360buyimg.com\/jgsq-productsoa\/jfs\/t14332\/56\/2342045055\/8025\/c40894c7\/5a990af1N2719ee6f.png\",\"endRemainTime\":0,\"wareId\":\"4647632\",\"expid\":\"100\",\"couponSortType\":0,\"sourceValue\":\"8_11_4647632_100_20_0_0_-100_2053e9f6fb6f81ebcae364a3d86d974c63a944bd_-100\",\"isFeedBackSlide\":0,\"benefitTime\":\"6.14\",\"category1\":\"1318\",\"category3\":\"1480\",\"category2\":\"1462\",\"canAddCart\":\"0\",\"sourceValueSimilar\":\"0_.6_11_4647632_100_8_20_0_0\",\"wname\":\"贝美星望远镜 10×22小单筒望远镜 便携高倍高清 户外观景体育赛事演唱会适用 BMX1022-XD\",\"stockStateId\":33,\"promotion\":\"false\",\"benefitTitle\":\"每满99减20，上不封顶\",\"markFlag\":1,\"isPlusWare\":false,\"remainNum\":-1,\"canNegFeedback\":\"1\",\"feminine\":false,\"similarEnter\":\"1\",\"canFreeRead\":\"false\",\"imageurl\":\"http:\/\/m.360buyimg.com\/mobilecms\/s276x276_jfs\/t5044\/296\/103622621\/184813\/1e42366b\/58da726cN01a11a9b.jpg!q70.jpg\",\"sid\":\"0\",\"mp\":0,\"startRemainTime\":0,\"itemType\":0,\"commentCount\":\"23844\",\"source\":\"0\",\"reqsig\":\"2053e9f6fb6f81ebcae364a3d86d974c63a944bd\",\"book\":\"false\",\"clickUrl\":\"http:\/\/mercury.jd.com\/log.gif?t=rec.619128&v=src=rec$action=1$reqsig=2053e9f6fb6f81ebcae364a3d86d974c63a944bd$enb=1$sku=0$p=619128$pin=$uuid=15160196181341028780571$csku=4647632$index=11$st=0$adcli=$expid=100$im=&rid=1752306307541895661&ver=1&sig=a4fb1cee829f27ac883ccf20d9c2948b3d883e4f\",\"exposureSourceValue\":\"4647632#2053e9f6fb6f81ebcae364a3d86d974c63a944bd#0#20#0#0#100#-100#-100#8#11#0\"},{\"adword\":\"\",\"presaleWare\":0,\"isDotScheme\":false,\"jdShop\":false,\"sourceValueFeedback\":\"{\\\"sid\\\":\\\"0\\\",\\\"index\\\":\\\"12\\\",\\\"source\\\":\\\"0\\\",\\\"page\\\":\\\"8\\\",\\\"reqsig\\\":\\\"2053e9f6fb6f81ebcae364a3d86d974c63a944bd\\\",\\\"flow\\\":\\\"20\\\",\\\"skuid\\\":\\\"6011537\\\",\\\"expid\\\":\\\"100\\\"}\",\"venderId\":\"1000088846\",\"followCount\":\"\",\"jdPrice\":\"239.00\",\"isPinGouWare\":false,\"good\":\"100%\",\"flow\":\"20\",\"imageurlType\":0,\"isSamWare\":false,\"abt\":\"\",\"benefitImageUrl\":\"http:\/\/img30.360buyimg.com\/jgsq-productsoa\/jfs\/t14332\/56\/2342045055\/8025\/c40894c7\/5a990af1N2719ee6f.png\",\"recomText\":\"满199元减50元\",\"iconC\":\"tab_020\",\"endRemainTime\":0,\"wareId\":\"6011537\",\"expid\":\"100\",\"couponSortType\":0,\"sourceValue\":\"8_12_6011537_100_20_0_0_-100_2053e9f6fb6f81ebcae364a3d86d974c63a944bd_-100\",\"isFeedBackSlide\":0,\"benefitTime\":\"6.5-6.15\",\"category1\":\"6144\",\"category3\":\"6193\",\"category2\":\"6182\",\"canAddCart\":\"0\",\"sourceValueSimilar\":\"0_.6_12_6011537_100_8_20_0_0\",\"wname\":\"Shes茜子七夕礼物送女友胸针胸花复古丁香花朵女配饰别针开衫插针 C1蓝色 均码\",\"stockStateId\":33,\"promotion\":\"false\",\"benefitTitle\":\"满199减50\/399减100\",\"markFlag\":1,\"isPlusWare\":false,\"remainNum\":-1,\"canNegFeedback\":\"1\",\"feminine\":false,\"similarEnter\":\"1\",\"canFreeRead\":\"false\",\"imageurl\":\"http:\/\/m.360buyimg.com\/mobilecms\/s276x276_jfs\/t15475\/205\/1914455107\/366494\/8bef3d66\/5a6aa381Nf4170cff.jpg!q70.jpg\",\"sid\":\"0\",\"mp\":0,\"startRemainTime\":0,\"itemType\":0,\"commentCount\":\"648\",\"source\":\"0\",\"reqsig\":\"2053e9f6fb6f81ebcae364a3d86d974c63a944bd\",\"book\":\"false\",\"clickUrl\":\"http:\/\/mercury.jd.com\/log.gif?t=rec.619128&v=src=rec$action=1$reqsig=2053e9f6fb6f81ebcae364a3d86d974c63a944bd$enb=1$sku=0$p=619128$pin=$uuid=15160196181341028780571$csku=6011537$index=12$st=0$adcli=$expid=100$im=&rid=1752306307541895661&ver=1&sig=6c819cbad5278bf95f70006e2fdfd60e01b75f98\",\"exposureSourceValue\":\"6011537#2053e9f6fb6f81ebcae364a3d86d974c63a944bd#0#20#0#0#100#满减#-100#8#12#0\"},{\"presaleWare\":0,\"stockStateId\":33,\"wname\":\"天艺牌理发老式剃刀*刮胡刀*手动剃头刀*家用刮脸刀*剃须刀修胡型 剃须刀+荡刀布+磨刀蜡+剃须刷\",\"adword\":\"\",\"isDotScheme\":false,\"jdShop\":false,\"sourceValueFeedback\":\"{\\\"sid\\\":\\\"0\\\",\\\"index\\\":\\\"13\\\",\\\"source\\\":\\\"0\\\",\\\"page\\\":\\\"8\\\",\\\"reqsig\\\":\\\"2053e9f6fb6f81ebcae364a3d86d974c63a944bd\\\",\\\"flow\\\":\\\"20\\\",\\\"skuid\\\":\\\"10340998631\\\",\\\"expid\\\":\\\"100\\\"}\",\"promotion\":\"false\",\"venderId\":\"37542\",\"isPinGouWare\":false,\"jdPrice\":\"47.50\",\"followCount\":\"\",\"good\":\"91%\",\"flow\":\"20\",\"markFlag\":0,\"imageurlType\":0,\"isPlusWare\":false,\"remainNum\":-1,\"isSamWare\":false,\"abt\":\"\",\"canNegFeedback\":\"1\",\"endRemainTime\":0,\"similarEnter\":\"1\",\"feminine\":false,\"canFreeRead\":\"false\",\"imageurl\":\"http:\/\/m.360buyimg.com\/mobilecms\/s276x276_jfs\/t15562\/102\/2583424350\/281068\/1ae0240\/5ab46862N7f3594b5.jpg!q70.jpg\",\"wareId\":\"10340998631\",\"expid\":\"100\",\"couponSortType\":0,\"mainVideoId\":\"6320746\",\"sourceValue\":\"8_13_10340998631_100_20_0_0_-100_2053e9f6fb6f81ebcae364a3d86d974c63a944bd_-100\",\"sid\":\"0\",\"mp\":0,\"startRemainTime\":0,\"itemType\":0,\"isFeedBackSlide\":0,\"category1\":\"1316\",\"category3\":\"1416\",\"commentCount\":\"4403\",\"canAddCart\":\"0\",\"category2\":\"1381\",\"source\":\"0\",\"sourceValueSimilar\":\"0_.6_13_10340998631_100_8_20_0_0\",\"reqsig\":\"2053e9f6fb6f81ebcae364a3d86d974c63a944bd\",\"book\":\"false\",\"clickUrl\":\"http:\/\/mercury.jd.com\/log.gif?t=rec.619128&v=src=rec$action=1$reqsig=2053e9f6fb6f81ebcae364a3d86d974c63a944bd$enb=1$sku=0$p=619128$pin=$uuid=15160196181341028780571$csku=10340998631$index=13$st=0$adcli=$expid=100$im=&rid=1752306307541895661&ver=1&sig=c22019e58ac0309b3c7fa44e6845d95901cf6685\",\"exposureSourceValue\":\"10340998631#2053e9f6fb6f81ebcae364a3d86d974c63a944bd#0#20#0#0#100#-100#-100#8#13#0\"},{\"adword\":\"\",\"presaleWare\":0,\"isDotScheme\":false,\"jdShop\":false,\"sourceValueFeedback\":\"{\\\"sid\\\":\\\"0\\\",\\\"index\\\":\\\"14\\\",\\\"source\\\":\\\"0\\\",\\\"page\\\":\\\"8\\\",\\\"reqsig\\\":\\\"2053e9f6fb6f81ebcae364a3d86d974c63a944bd\\\",\\\"flow\\\":\\\"20\\\",\\\"skuid\\\":\\\"28799866029\\\",\\\"expid\\\":\\\"100\\\"}\",\"venderId\":\"754969\",\"followCount\":\"\",\"jdPrice\":\"89.90\",\"isPinGouWare\":false,\"good\":\"100%\",\"flow\":\"20\",\"imageurlType\":0,\"isSamWare\":false,\"abt\":\"\",\"benefitImageUrl\":\"http:\/\/img30.360buyimg.com\/jgsq-productsoa\/jfs\/t14332\/56\/2342045055\/8025\/c40894c7\/5a990af1N2719ee6f.png\",\"recomText\":\"满100元减10元\",\"iconC\":\"tab_020\",\"endRemainTime\":0,\"wareId\":\"28799866029\",\"expid\":\"100\",\"couponSortType\":0,\"sourceValue\":\"8_14_28799866029_100_20_0_0_-100_2053e9f6fb6f81ebcae364a3d86d974c63a944bd_-100\",\"isFeedBackSlide\":0,\"benefitTime\":\"6.12-6.13\",\"category1\":\"6196\",\"category3\":\"11977\",\"category2\":\"6214\",\"canAddCart\":\"0\",\"sourceValueSimilar\":\"0_.6_14_28799866029_100_8_20_0_0\",\"wname\":\"艾杰普（JEPPE） 厨房置物架 壁挂免打孔厨具收纳刀架调料架筷子筒 厨房用品 双杯60CM\",\"stockStateId\":33,\"promotion\":\"false\",\"benefitTitle\":\"家居好物跨店3件7折\",\"markFlag\":1,\"isPlusWare\":false,\"remainNum\":-1,\"canNegFeedback\":\"1\",\"feminine\":false,\"similarEnter\":\"1\",\"canFreeRead\":\"false\",\"imageurl\":\"http:\/\/m.360buyimg.com\/mobilecms\/s276x276_jfs\/t20638\/71\/795531159\/484960\/3aaccc\/5b19052eN7fd88c8b.jpg!q70.jpg\",\"sid\":\"0\",\"mp\":0,\"startRemainTime\":0,\"itemType\":0,\"commentCount\":\"2270\",\"source\":\"0\",\"reqsig\":\"2053e9f6fb6f81ebcae364a3d86d974c63a944bd\",\"book\":\"false\",\"clickUrl\":\"http:\/\/mercury.jd.com\/log.gif?t=rec.619128&v=src=rec$action=1$reqsig=2053e9f6fb6f81ebcae364a3d86d974c63a944bd$enb=1$sku=0$p=619128$pin=$uuid=15160196181341028780571$csku=28799866029$index=14$st=0$adcli=$expid=100$im=&rid=1752306307541895661&ver=1&sig=e1f453dd6466c0baf95570b0d37fb1d677f9093f\",\"exposureSourceValue\":\"28799866029#2053e9f6fb6f81ebcae364a3d86d974c63a944bd#0#20#0#0#100#满减#-100#8#14#0\"},{\"adword\":\"\",\"presaleWare\":0,\"isDotScheme\":false,\"sourceValueFeedback\":\"{\\\"sid\\\":\\\"0\\\",\\\"index\\\":\\\"15\\\",\\\"source\\\":\\\"0\\\",\\\"page\\\":\\\"8\\\",\\\"reqsig\\\":\\\"2053e9f6fb6f81ebcae364a3d86d974c63a944bd\\\",\\\"flow\\\":\\\"20\\\",\\\"skuid\\\":\\\"6309950\\\",\\\"expid\\\":\\\"100\\\"}\",\"jdShop\":false,\"venderId\":\"1000004123\",\"followCount\":\"\",\"jdPrice\":\"299.00\",\"isPinGouWare\":false,\"good\":\"99%\",\"flow\":\"20\",\"imageurlType\":0,\"icon618\":\"1\",\"isSamWare\":false,\"abt\":\"\",\"isShowIcon618\":true,\"endRemainTime\":0,\"wareId\":\"6309950\",\"expid\":\"100\",\"couponSortType\":0,\"sourceValue\":\"8_15_6309950_100_20_0_0_-100_2053e9f6fb6f81ebcae364a3d86d974c63a944bd_-100\",\"isFeedBackSlide\":0,\"category1\":\"670\",\"category3\":\"11304\",\"category2\":\"699\",\"canAddCart\":\"0\",\"icon618Img\":\"\/\/m.360buyimg.com\/cc\/jfs\/t18418\/267\/2552089660\/923\/5efef8f7\/5afbd692Nda78a09e.png\",\"sourceValueSimilar\":\"0_.6_15_6309950_100_8_20_0_0\",\"wname\":\"小米（MI）小米盒子4 智能网络电视机顶盒 4K电视 H.265硬解 安卓网络盒子 高清网络播放器 HDR 白色\",\"stockStateId\":33,\"promotion\":\"false\",\"markFlag\":0,\"isPlusWare\":false,\"remainNum\":-1,\"canNegFeedback\":\"1\",\"feminine\":false,\"similarEnter\":\"1\",\"canFreeRead\":\"false\",\"imageurl\":\"http:\/\/m.360buyimg.com\/mobilecms\/s276x276_jfs\/t15610\/19\/2016315278\/49207\/5188d542\/5a70208eNe58804fe.jpg!q70.jpg\",\"sid\":\"0\",\"mp\":0,\"startRemainTime\":0,\"itemType\":0,\"commentCount\":\"482932\",\"source\":\"0\",\"reqsig\":\"2053e9f6fb6f81ebcae364a3d86d974c63a944bd\",\"book\":\"false\",\"clickUrl\":\"http:\/\/mercury.jd.com\/log.gif?t=rec.619128&v=src=rec$action=1$reqsig=2053e9f6fb6f81ebcae364a3d86d974c63a944bd$enb=1$sku=0$p=619128$pin=$uuid=15160196181341028780571$csku=6309950$index=15$st=0$adcli=$expid=100$im=&rid=1752306307541895661&ver=1&sig=47091b804b308da7d9af0a50eb5c9a87e419bd91\",\"exposureSourceValue\":\"6309950#2053e9f6fb6f81ebcae364a3d86d974c63a944bd#0#20#0#0#100#-100#-100#8#15#1\"},{\"adword\":\"\",\"presaleWare\":0,\"isDotScheme\":false,\"sourceValueFeedback\":\"{\\\"sid\\\":\\\"0\\\",\\\"index\\\":\\\"16\\\",\\\"source\\\":\\\"0\\\",\\\"page\\\":\\\"8\\\",\\\"reqsig\\\":\\\"2053e9f6fb6f81ebcae364a3d86d974c63a944bd\\\",\\\"flow\\\":\\\"20\\\",\\\"skuid\\\":\\\"4034694\\\",\\\"expid\\\":\\\"100\\\"}\",\"jdShop\":false,\"venderId\":\"1000010552\",\"followCount\":\"\",\"jdPrice\":\"89.00\",\"isPinGouWare\":false,\"good\":\"100%\",\"flow\":\"20\",\"imageurlType\":0,\"icon618\":\"1\",\"isSamWare\":false,\"abt\":\"\",\"isShowIcon618\":true,\"endRemainTime\":0,\"wareId\":\"4034694\",\"expid\":\"100\",\"couponSortType\":0,\"sourceValue\":\"8_16_4034694_100_20_0_0_-100_2053e9f6fb6f81ebcae364a3d86d974c63a944bd_-100\",\"isFeedBackSlide\":0,\"category1\":\"737\",\"category3\":\"759\",\"category2\":\"752\",\"canAddCart\":\"0\",\"icon618Img\":\"\/\/m.360buyimg.com\/cc\/jfs\/t18418\/267\/2552089660\/923\/5efef8f7\/5afbd692Nda78a09e.png\",\"sourceValueSimilar\":\"0_.6_16_4034694_100_8_20_0_0\",\"wname\":\"康佳（KONKA）电烤箱家用多功能 12L迷你烘焙小烤箱 KAO-1208\",\"stockStateId\":33,\"promotion\":\"false\",\"markFlag\":0,\"isPlusWare\":false,\"remainNum\":-1,\"canNegFeedback\":\"1\",\"feminine\":false,\"similarEnter\":\"1\",\"canFreeRead\":\"false\",\"imageurl\":\"http:\/\/m.360buyimg.com\/mobilecms\/s276x276_jfs\/t20215\/353\/372557260\/282352\/417bed28\/5b0b7d6fN7325ee39.jpg!q70.jpg\",\"sid\":\"0\",\"mainVideoId\":\"378427\",\"mp\":0,\"startRemainTime\":0,\"itemType\":0,\"commentCount\":\"38227\",\"source\":\"0\",\"reqsig\":\"2053e9f6fb6f81ebcae364a3d86d974c63a944bd\",\"book\":\"false\",\"clickUrl\":\"http:\/\/mercury.jd.com\/log.gif?t=rec.619128&v=src=rec$action=1$reqsig=2053e9f6fb6f81ebcae364a3d86d974c63a944bd$enb=1$sku=0$p=619128$pin=$uuid=15160196181341028780571$csku=4034694$index=16$st=0$adcli=$expid=100$im=&rid=1752306307541895661&ver=1&sig=d25798216b91933feff12bfdfba3a5a5d79fde68\",\"exposureSourceValue\":\"4034694#2053e9f6fb6f81ebcae364a3d86d974c63a944bd#0#20#0#0#100#-100#-100#8#16#1\"},{\"adword\":\"\",\"presaleWare\":0,\"isDotScheme\":false,\"markHeight\":13,\"jdShop\":false,\"sourceValueFeedback\":\"{\\\"sid\\\":\\\"0\\\",\\\"index\\\":\\\"17\\\",\\\"source\\\":\\\"0\\\",\\\"page\\\":\\\"8\\\",\\\"reqsig\\\":\\\"2053e9f6fb6f81ebcae364a3d86d974c63a944bd\\\",\\\"flow\\\":\\\"20\\\",\\\"skuid\\\":\\\"4911033\\\",\\\"expid\\\":\\\"100\\\"}\",\"venderId\":\"1000072435\",\"followCount\":\"\",\"jdPrice\":\"189.00\",\"isPinGouWare\":false,\"good\":\"100%\",\"flow\":\"20\",\"imageurlType\":0,\"isSamWare\":false,\"abt\":\"\",\"benefitImageUrl\":\"http:\/\/img30.360buyimg.com\/jgsq-productsoa\/jfs\/t14332\/56\/2342045055\/8025\/c40894c7\/5a990af1N2719ee6f.png\",\"recomText\":\"\",\"iconC\":\"tab_020\",\"endRemainTime\":0,\"wareId\":\"4911033\",\"expid\":\"100\",\"couponSortType\":0,\"sourceValue\":\"8_17_4911033_100_20_0_0_-100_2053e9f6fb6f81ebcae364a3d86d974c63a944bd_-100\",\"isFeedBackSlide\":0,\"benefitTime\":\"6.11-6.14\",\"category1\":\"1318\",\"category3\":\"12122\",\"category2\":\"1466\",\"canAddCart\":\"0\",\"markImageUrl\":\"http:\/\/m.360buyimg.com\/mobilecms\/jfs\/t3802\/184\/2262265095\/4363\/20cc83a\/584675ccNb39899f9.png\",\"sourceValueSimilar\":\"0_.6_17_4911033_100_8_20_0_0\",\"wname\":\"史努比 SNOOPY 滑板车儿童 一秒折叠升降闪光四轮踏板车 蓝色SN7001\",\"stockStateId\":36,\"markWidth\":50,\"promotion\":\"false\",\"benefitTitle\":\"领券满299-80 499-120\",\"markFlag\":1,\"isPlusWare\":false,\"remainNum\":-1,\"canNegFeedback\":\"1\",\"feminine\":false,\"similarEnter\":\"1\",\"canFreeRead\":\"false\",\"imageurl\":\"http:\/\/m.360buyimg.com\/mobilecms\/s276x276_jfs\/t18799\/365\/2024058478\/141640\/e7e0c34\/5ae1986fN81742516.jpg!q70.jpg\",\"sid\":\"0\",\"mp\":0,\"startRemainTime\":0,\"itemType\":0,\"commentCount\":\"7207\",\"source\":\"0\",\"reqsig\":\"2053e9f6fb6f81ebcae364a3d86d974c63a944bd\",\"book\":\"false\",\"clickUrl\":\"http:\/\/mercury.jd.com\/log.gif?t=rec.619128&v=src=rec$action=1$reqsig=2053e9f6fb6f81ebcae364a3d86d974c63a944bd$enb=1$sku=0$p=619128$pin=$uuid=15160196181341028780571$csku=4911033$index=17$st=0$adcli=$expid=100$im=&rid=1752306307541895661&ver=1&sig=c96952fb197914dc1eaee2641206d09a7157e83a\",\"exposureSourceValue\":\"4911033#2053e9f6fb6f81ebcae364a3d86d974c63a944bd#0#20#0#0#100#满减#-100#8#17#0\",\"wareType\":8},{\"presaleWare\":0,\"stockStateId\":33,\"wname\":\"吉列（Gillette）吉列锋隐手动剃须刀5层刀片手动剃须刀 锋隐4刀头（不含刀架）\",\"adword\":\"\",\"isDotScheme\":false,\"jdShop\":false,\"sourceValueFeedback\":\"{\\\"sid\\\":\\\"0\\\",\\\"index\\\":\\\"18\\\",\\\"source\\\":\\\"0\\\",\\\"page\\\":\\\"8\\\",\\\"reqsig\\\":\\\"2053e9f6fb6f81ebcae364a3d86d974c63a944bd\\\",\\\"flow\\\":\\\"20\\\",\\\"skuid\\\":\\\"24274085093\\\",\\\"expid\\\":\\\"100\\\"}\",\"promotion\":\"false\",\"venderId\":\"741721\",\"isPinGouWare\":false,\"jdPrice\":\"80.00\",\"followCount\":\"\",\"good\":\"100%\",\"flow\":\"20\",\"markFlag\":0,\"imageurlType\":0,\"isPlusWare\":false,\"remainNum\":-1,\"isSamWare\":false,\"abt\":\"\",\"canNegFeedback\":\"1\",\"endRemainTime\":0,\"similarEnter\":\"1\",\"feminine\":false,\"canFreeRead\":\"false\",\"imageurl\":\"http:\/\/m.360buyimg.com\/mobilecms\/s276x276_jfs\/t16324\/327\/1517293310\/256482\/c690ecfa\/5a558079Nd6238bad.jpg!q70.jpg\",\"wareId\":\"24274085093\",\"expid\":\"100\",\"couponSortType\":0,\"sourceValue\":\"8_18_24274085093_100_20_0_0_-100_2053e9f6fb6f81ebcae364a3d86d974c63a944bd_-100\",\"sid\":\"0\",\"mp\":0,\"startRemainTime\":0,\"itemType\":0,\"isFeedBackSlide\":0,\"category1\":\"1316\",\"category3\":\"1416\",\"commentCount\":\"153\",\"canAddCart\":\"0\",\"category2\":\"1381\",\"source\":\"0\",\"sourceValueSimilar\":\"0_.6_18_24274085093_100_8_20_0_0\",\"reqsig\":\"2053e9f6fb6f81ebcae364a3d86d974c63a944bd\",\"book\":\"false\",\"clickUrl\":\"http:\/\/mercury.jd.com\/log.gif?t=rec.619128&v=src=rec$action=1$reqsig=2053e9f6fb6f81ebcae364a3d86d974c63a944bd$enb=1$sku=0$p=619128$pin=$uuid=15160196181341028780571$csku=24274085093$index=18$st=0$adcli=$expid=100$im=&rid=1752306307541895661&ver=1&sig=4086291c06e655db3d0ce121241d28c1e164b3a\",\"exposureSourceValue\":\"24274085093#2053e9f6fb6f81ebcae364a3d86d974c63a944bd#0#20#0#0#100#-100#-100#8#18#0\"},{\"adword\":\"\",\"presaleWare\":0,\"isDotScheme\":false,\"sourceValueFeedback\":\"{\\\"sid\\\":\\\"0\\\",\\\"index\\\":\\\"19\\\",\\\"source\\\":\\\"0\\\",\\\"page\\\":\\\"8\\\",\\\"reqsig\\\":\\\"2053e9f6fb6f81ebcae364a3d86d974c63a944bd\\\",\\\"flow\\\":\\\"20\\\",\\\"skuid\\\":\\\"21006112282\\\",\\\"expid\\\":\\\"100\\\"}\",\"jdShop\":false,\"venderId\":\"164122\",\"followCount\":\"\",\"jdPrice\":\"158.00\",\"isPinGouWare\":false,\"good\":\"100%\",\"flow\":\"20\",\"imageurlType\":0,\"icon618\":\"1\",\"isSamWare\":false,\"abt\":\"\",\"isShowIcon618\":true,\"recomText\":\"\",\"iconC\":\"tab_020\",\"endRemainTime\":0,\"wareId\":\"21006112282\",\"expid\":\"100\",\"couponSortType\":0,\"sourceValue\":\"8_19_21006112282_100_20_0_0_-100_2053e9f6fb6f81ebcae364a3d86d974c63a944bd_-100\",\"isFeedBackSlide\":0,\"category1\":\"1318\",\"category3\":\"1480\",\"category2\":\"1462\",\"canAddCart\":\"0\",\"icon618Img\":\"\/\/m.360buyimg.com\/cc\/jfs\/t18418\/267\/2552089660\/923\/5efef8f7\/5afbd692Nda78a09e.png\",\"sourceValueSimilar\":\"0_.6_19_21006112282_100_8_20_0_0\",\"wname\":\"千里鹰（QANLIIY）便携双筒望远镜升级版 高倍高清微光夜视非红外演唱会拍照望眼镜 猎鹰60X25升级版+军刀+手机夹\",\"stockStateId\":33,\"promotion\":\"false\",\"markFlag\":0,\"isPlusWare\":false,\"remainNum\":-1,\"canNegFeedback\":\"1\",\"feminine\":false,\"similarEnter\":\"1\",\"canFreeRead\":\"false\",\"imageurl\":\"http:\/\/m.360buyimg.com\/mobilecms\/s276x276_jfs\/t19762\/224\/2685188664\/283807\/4a2d1c2a\/5b03dbd1Na013f2e6.jpg!q70.jpg\",\"sid\":\"0\",\"mp\":0,\"startRemainTime\":0,\"itemType\":0,\"commentCount\":\"10682\",\"source\":\"0\",\"reqsig\":\"2053e9f6fb6f81ebcae364a3d86d974c63a944bd\",\"book\":\"false\",\"clickUrl\":\"http:\/\/mercury.jd.com\/log.gif?t=rec.619128&v=src=rec$action=1$reqsig=2053e9f6fb6f81ebcae364a3d86d974c63a944bd$enb=1$sku=0$p=619128$pin=$uuid=15160196181341028780571$csku=21006112282$index=19$st=0$adcli=$expid=100$im=&rid=1752306307541895661&ver=1&sig=e12a1d80fe33bf6c5bfba9ee46368d26289ee2f8\",\"exposureSourceValue\":\"21006112282#2053e9f6fb6f81ebcae364a3d86d974c63a944bd#0#20#0#0#100#满减#-100#8#19#1\"},{\"adword\":\"\",\"presaleWare\":0,\"isDotScheme\":false,\"sourceValueFeedback\":\"{\\\"sid\\\":\\\"0\\\",\\\"index\\\":\\\"20\\\",\\\"source\\\":\\\"0\\\",\\\"page\\\":\\\"8\\\",\\\"reqsig\\\":\\\"2053e9f6fb6f81ebcae364a3d86d974c63a944bd\\\",\\\"flow\\\":\\\"20\\\",\\\"skuid\\\":\\\"1400281\\\",\\\"expid\\\":\\\"100\\\"}\",\"jdShop\":false,\"venderId\":\"1000001465\",\"followCount\":\"\",\"jdPrice\":\"179.00\",\"isPinGouWare\":false,\"good\":\"99%\",\"flow\":\"20\",\"imageurlType\":0,\"icon618\":\"1\",\"isSamWare\":false,\"abt\":\"\",\"isShowIcon618\":true,\"endRemainTime\":0,\"wareId\":\"1400281\",\"expid\":\"100\",\"couponSortType\":0,\"sourceValue\":\"8_20_1400281_100_20_0_0_-100_2053e9f6fb6f81ebcae364a3d86d974c63a944bd_-100\",\"isFeedBackSlide\":0,\"category1\":\"737\",\"category3\":\"759\",\"category2\":\"752\",\"canAddCart\":\"0\",\"icon618Img\":\"\/\/m.360buyimg.com\/cc\/jfs\/t18418\/267\/2552089660\/923\/5efef8f7\/5afbd692Nda78a09e.png\",\"sourceValueSimilar\":\"0_.6_20_1400281_100_8_20_0_0\",\"wname\":\"九阳（Joyoung）电烤箱 30L 家用多功能 专业烘焙 KX-30J601\",\"stockStateId\":33,\"promotion\":\"false\",\"markFlag\":0,\"isPlusWare\":false,\"remainNum\":-1,\"canNegFeedback\":\"1\",\"feminine\":false,\"similarEnter\":\"1\",\"canFreeRead\":\"false\",\"imageurl\":\"http:\/\/m.360buyimg.com\/mobilecms\/s276x276_jfs\/t21919\/103\/432927131\/283047\/93225fe3\/5b0cc7d0N1ff28a4f.jpg!q70.jpg\",\"sid\":\"0\",\"mp\":0,\"startRemainTime\":0,\"itemType\":0,\"commentCount\":\"82347\",\"source\":\"0\",\"reqsig\":\"2053e9f6fb6f81ebcae364a3d86d974c63a944bd\",\"book\":\"false\",\"clickUrl\":\"http:\/\/mercury.jd.com\/log.gif?t=rec.619128&v=src=rec$action=1$reqsig=2053e9f6fb6f81ebcae364a3d86d974c63a944bd$enb=1$sku=0$p=619128$pin=$uuid=15160196181341028780571$csku=1400281$index=20$st=0$adcli=$expid=100$im=&rid=1752306307541895661&ver=1&sig=1be5d89ef85a4f2d18664a6ac46212045bda9aeb\",\"exposureSourceValue\":\"1400281#2053e9f6fb6f81ebcae364a3d86d974c63a944bd#0#20#0#0#100#-100#-100#8#20#1\"},{\"presaleWare\":0,\"stockStateId\":33,\"wname\":\"名士（Ming Shi） 手动剃须刀老式新款刮胡刀可调锋利度旋开式双面刀架配双面刀片包邮 标配（银色刀架+10刀片+盒子）\",\"adword\":\"\",\"isDotScheme\":false,\"jdShop\":false,\"sourceValueFeedback\":\"{\\\"sid\\\":\\\"0\\\",\\\"index\\\":\\\"21\\\",\\\"source\\\":\\\"0\\\",\\\"page\\\":\\\"8\\\",\\\"reqsig\\\":\\\"2053e9f6fb6f81ebcae364a3d86d974c63a944bd\\\",\\\"flow\\\":\\\"20\\\",\\\"skuid\\\":\\\"24375284092\\\",\\\"expid\\\":\\\"100\\\"}\",\"promotion\":\"false\",\"venderId\":\"622358\",\"isPinGouWare\":false,\"jdPrice\":\"42.90\",\"followCount\":\"\",\"good\":\"98%\",\"flow\":\"20\",\"markFlag\":0,\"imageurlType\":0,\"isPlusWare\":false,\"remainNum\":-1,\"isSamWare\":false,\"abt\":\"\",\"canNegFeedback\":\"1\",\"endRemainTime\":0,\"similarEnter\":\"1\",\"feminine\":false,\"canFreeRead\":\"false\",\"imageurl\":\"http:\/\/m.360buyimg.com\/mobilecms\/s276x276_jfs\/t19420\/147\/1005736767\/112518\/300cd924\/5ab5d613Na1bf31b3.jpg!q70.jpg\",\"wareId\":\"24375284092\",\"expid\":\"100\",\"couponSortType\":0,\"mainVideoId\":\"5082190\",\"sourceValue\":\"8_21_24375284092_100_20_0_0_-100_2053e9f6fb6f81ebcae364a3d86d974c63a944bd_-100\",\"sid\":\"0\",\"mp\":0,\"startRemainTime\":0,\"itemType\":0,\"isFeedBackSlide\":0,\"category1\":\"1316\",\"category3\":\"1416\",\"commentCount\":\"1211\",\"canAddCart\":\"0\",\"category2\":\"1381\",\"source\":\"0\",\"sourceValueSimilar\":\"0_.6_21_24375284092_100_8_20_0_0\",\"reqsig\":\"2053e9f6fb6f81ebcae364a3d86d974c63a944bd\",\"book\":\"false\",\"clickUrl\":\"http:\/\/mercury.jd.com\/log.gif?t=rec.619128&v=src=rec$action=1$reqsig=2053e9f6fb6f81ebcae364a3d86d974c63a944bd$enb=1$sku=0$p=619128$pin=$uuid=15160196181341028780571$csku=24375284092$index=21$st=0$adcli=$expid=100$im=&rid=1752306307541895661&ver=1&sig=ca962f281398aee91bf40968f1d015fded6dfa11\",\"exposureSourceValue\":\"24375284092#2053e9f6fb6f81ebcae364a3d86d974c63a944bd#0#20#0#0#100#-100#-100#8#21#0\"}],\"expid\":\"619128\"}"
}